blite_tracing/__init__.py
blite_tracing/py.typed
blite_tracing/trace.py
blite_tracing-0.1.1.dist-info/METADATA
blite_tracing-0.1.1.dist-info/WHEEL
blite_tracing-0.1.1.dist-info/RECORD
