Metadata-Version: 2.4
Name: blite-tracing
Version: 0.1.1
Summary: Add your description here
Author-email: Pankaj Gupta <pankaj.roark@gmail.com>
Requires-Python: >=3.9
